fleming/__init__.py
fleming/fleming.py
fleming/version.py
fleming-0.7.0.dist-info/LICENSE.rst
fleming-0.7.0.dist-info/METADATA
fleming-0.7.0.dist-info/WHEEL
fleming-0.7.0.dist-info/top_level.txt
fleming-0.7.0.dist-info/RECORD
