Metadata-Version: 1.1
Name: fleming
Version: 0.7.0
Summary: Python helpers for manipulating datetime objects relative to time zones
Home-page: https://github.com/ambitioninc/fleming
Author: Wes Kendall
Author-email: wesleykendall@gmail.com
License: MIT
Keywords: python datetime pytz timezone timedelta arithmetic floor conversion
Platform: UNKNOWN
Classifier: Topic :: Utilities
Classifier: Topic :: Software Development :: Libraries :: Python Modules
Classifier: License :: OSI Approved :: MIT License
Classifier: Programming Language :: Python :: 3.7
Classifier: Programming Language :: Python :: 3.8
Classifier: Programming Language :: Python :: 3.9
